{
	"configurations" : 
	[
		{
			"directories" : 
			[
				{
					"build" : ".",
					"childIndexes" : 
					[
						1
					],
					"jsonFile" : "directory-.-Debug-d0094a50bb2071803777.json",
					"minimumCMakeVersion" : 
					{
						"string" : "3.22.1"
					},
					"projectIndex" : 0,
					"source" : ".",
					"targetIndexes" : 
					[
						2
					]
				},
				{
					"build" : "test",
					"jsonFile" : "directory-test-Debug-f18be1977b403cfd1a50.json",
					"minimumCMakeVersion" : 
					{
						"string" : "3.22.1"
					},
					"parentIndex" : 0,
					"projectIndex" : 1,
					"source" : "test",
					"targetIndexes" : 
					[
						0,
						1,
						3,
						4,
						5,
						6,
						7,
						8
					]
				}
			],
			"name" : "Debug",
			"projects" : 
			[
				{
					"childIndexes" : 
					[
						1
					],
					"directoryIndexes" : 
					[
						0
					],
					"name" : "net",
					"targetIndexes" : 
					[
						2
					]
				},
				{
					"directoryIndexes" : 
					[
						1
					],
					"name" : "test",
					"parentIndex" : 0,
					"targetIndexes" : 
					[
						0,
						1,
						3,
						4,
						5,
						6,
						7,
						8
					]
				}
			],
			"targets" : 
			[
				{
					"directoryIndex" : 1,
					"id" : "circular_queue::@36f028580bb02cc8272a",
					"jsonFile" : "target-circular_queue-Debug-26e6e722cef13f1b0e70.json",
					"name" : "circular_queue",
					"projectIndex" : 1
				},
				{
					"directoryIndex" : 1,
					"id" : "multi_thread::@36f028580bb02cc8272a",
					"jsonFile" : "target-multi_thread-Debug-c69b583cf73b4f20b676.json",
					"name" : "multi_thread",
					"projectIndex" : 1
				},
				{
					"directoryIndex" : 0,
					"id" : "net::@6890427a1f51a3e7e1df",
					"jsonFile" : "target-net-Debug-3c5c862c26d3fbf67c98.json",
					"name" : "net",
					"projectIndex" : 0
				},
				{
					"directoryIndex" : 1,
					"id" : "recv_pocket::@36f028580bb02cc8272a",
					"jsonFile" : "target-recv_pocket-Debug-922ec52ee19302c0ff5c.json",
					"name" : "recv_pocket",
					"projectIndex" : 1
				},
				{
					"directoryIndex" : 1,
					"id" : "send_pocket::@36f028580bb02cc8272a",
					"jsonFile" : "target-send_pocket-Debug-a0b113d722d9baab931f.json",
					"name" : "send_pocket",
					"projectIndex" : 1
				},
				{
					"directoryIndex" : 1,
					"id" : "test1::@36f028580bb02cc8272a",
					"jsonFile" : "target-test1-Debug-9523193112208d723de3.json",
					"name" : "test1",
					"projectIndex" : 1
				},
				{
					"directoryIndex" : 1,
					"id" : "test_mblock::@36f028580bb02cc8272a",
					"jsonFile" : "target-test_mblock-Debug-68e46eeb1b2f6f19d72f.json",
					"name" : "test_mblock",
					"projectIndex" : 1
				},
				{
					"directoryIndex" : 1,
					"id" : "test_tcp_echo_client::@36f028580bb02cc8272a",
					"jsonFile" : "target-test_tcp_echo_client-Debug-67aa100fbb98d4350ada.json",
					"name" : "test_tcp_echo_client",
					"projectIndex" : 1
				},
				{
					"directoryIndex" : 1,
					"id" : "test_tcp_echo_server::@36f028580bb02cc8272a",
					"jsonFile" : "target-test_tcp_echo_server-Debug-d9c54be573879a692ae5.json",
					"name" : "test_tcp_echo_server",
					"projectIndex" : 1
				}
			]
		}
	],
	"kind" : "codemodel",
	"paths" : 
	{
		"build" : "F:/code/c++code/mini-tcpip/build",
		"source" : "F:/code/c++code/mini-tcpip"
	},
	"version" : 
	{
		"major" : 2,
		"minor" : 6
	}
}
